stoic_html/__init__.py
stoic_html-2021.9.3.dist-info/LICENSE
stoic_html-2021.9.3.dist-info/METADATA
stoic_html-2021.9.3.dist-info/WHEEL
stoic_html-2021.9.3.dist-info/top_level.txt
stoic_html-2021.9.3.dist-info/RECORD
