Metadata-Version: 2.1
Name: stoic-html
Version: 2021.9.3
Summary: Stoic HTML: A simple wrapper around Django's `format_html()`
Home-page: https://github.com/guettli/stoic-html
Author: Thomas Guettler
Author-email: guettliml.stoic-html@thomas-guettler.de
License: UNKNOWN
Platform: UNKNOWN
Classifier: Environment :: Web Environment
Classifier: Framework :: Django
Classifier: License :: OSI Approved :: MIT License
Classifier: Programming Language :: Python :: 3
Requires-Python: >=3.8
License-File: LICENSE
Requires-Dist: pytest-django
Requires-Dist: pytest-mock
Requires-Dist: Django
